api/__init__.py
api/chats.py
api/contacts.py
api/messages.py
api/viewsets.py
migrations/0001_initial.py
migrations/0002_chatconnections.py
migrations/0003_chatsessions.py
migrations/0004_remove_chat_messages.py
migrations/0005_chatextratitle.py
migrations/0006_chatsettings_delete_chatextratitle.py
migrations/0007_chatsettings_config.py
migrations/0008_alter_chatsettings_chat.py
migrations/__init__.py
oc_chat_django-1.0.0.dist-info/METADATA
oc_chat_django-1.0.0.dist-info/WHEEL
oc_chat_django-1.0.0.dist-info/top_level.txt
oc_chat_django-1.0.0.dist-info/RECORD
