Metadata-Version: 2.1
Name: oc-chat-django
Version: 1.0.0
Summary: The django 'chat' page of @tbscode's open-chat
Requires-Python: >=3.8, <4
Requires-Dist: httpx <0.28.0,>=0.20.0
Requires-Dist: attrs >=21.3.0
Requires-Dist: python-dateutil <3,>=2.8.0
